qmt_manager/__init__.py
qmt_manager/manager.py
qmt_manager/libs/xtquant/__init__.py
qmt_manager/libs/xtquant/datacenter.cp310-win_amd64.pyd
qmt_manager/libs/xtquant/datacenter.cp311-win_amd64.pyd
qmt_manager/libs/xtquant/datacenter.cp312-win_amd64.pyd
qmt_manager/libs/xtquant/datacenter.cp313-win_amd64.pyd
qmt_manager/libs/xtquant/datacenter.cp36-win_amd64.pyd
qmt_manager/libs/xtquant/datacenter.cp37-win_amd64.pyd
qmt_manager/libs/xtquant/datacenter.cp38-win_amd64.pyd
qmt_manager/libs/xtquant/datacenter.cp39-win_amd64.pyd
qmt_manager/libs/xtquant/datacenter_shared.dll
qmt_manager/libs/xtquant/libeay32.dll
qmt_manager/libs/xtquant/log4cxx.dll
qmt_manager/libs/xtquant/msvcp140.dll
qmt_manager/libs/xtquant/ssleay32.dll
qmt_manager/libs/xtquant/vcruntime140.dll
qmt_manager/libs/xtquant/xtconn.py
qmt_manager/libs/xtquant/xtconstant.py
qmt_manager/libs/xtquant/xtdata.ini
qmt_manager/libs/xtquant/xtdata.log4cxx
qmt_manager/libs/xtquant/xtdata.py
qmt_manager/libs/xtquant/xtdata_config.py
qmt_manager/libs/xtquant/xtdatacenter.py
qmt_manager/libs/xtquant/xtextend.py
qmt_manager/libs/xtquant/xtpythonclient.cp310-win_amd64.pyd
qmt_manager/libs/xtquant/xtpythonclient.cp311-win_amd64.pyd
qmt_manager/libs/xtquant/xtpythonclient.cp312-win_amd64.pyd
qmt_manager/libs/xtquant/xtpythonclient.cp313-win_amd64.pyd
qmt_manager/libs/xtquant/xtpythonclient.cp36-win_amd64.pyd
qmt_manager/libs/xtquant/xtpythonclient.cp37-win_amd64.pyd
qmt_manager/libs/xtquant/xtpythonclient.cp38-win_amd64.pyd
qmt_manager/libs/xtquant/xtpythonclient.cp39-win_amd64.pyd
qmt_manager/libs/xtquant/xtstocktype.py
qmt_manager/libs/xtquant/xttools.py
qmt_manager/libs/xtquant/xttrader.py
qmt_manager/libs/xtquant/xttype.py
qmt_manager/libs/xtquant/xtutil.py
qmt_manager/libs/xtquant/xtview.py
qmt_manager/libs/xtquant/__pycache__/__init__.cpython-311.pyc
qmt_manager/libs/xtquant/__pycache__/__init__.cpython-39.pyc
qmt_manager/libs/xtquant/__pycache__/xtconn.cpython-39.pyc
qmt_manager-1.0.2.dist-info/licenses/LICENSE.md
qmt_manager-1.0.2.dist-info/METADATA
qmt_manager-1.0.2.dist-info/WHEEL
qmt_manager-1.0.2.dist-info/entry_points.txt
qmt_manager-1.0.2.dist-info/top_level.txt
qmt_manager-1.0.2.dist-info/RECORD
